{
    "depends": [
        "bat",
        "fzf",
        "ripgrep",
        "everything-cli",
        "neovim",
        "clink"
    ],
    "version": "0.5.1",
    "description": "Fast directory alias resolver - type 'o acme' from any prompt and your shell jumps to the project root",
    "homepage": "https://github.com/sadirano/onix",
    "license": "MIT",
    "architecture": {
        "64bit": {
            "url": "https://github.com/sadirano/onix/releases/download/v0.5.1/onix-v0.5.1-windows-amd64.zip",
            "hash": "112dc367dd9fa40e62abdabaeca89a1b7c4e714e3e3267436a80fb4c6dd22e51"
        }
    },
    "bin": "onix.exe",
    "post_install": [
        "onix --init",
        "clink autorun install | Out-Null",
        "clink set autosuggest.inline true | Out-Null"
    ],
    "checkver": {
        "github": "https://github.com/sadirano/onix"
    },
    "autoupdate": {
        "architecture": {
            "64bit": {
                "url": "https://github.com/sadirano/onix/releases/download/v$version/onix-v$version-windows-amd64.zip"
            }
        }
    }
}
